{
  "results": [
    {
      "title": "CSCI   12 - Introduction to Computers and Computation",
      "nbr": "65363",
      "time": "MoWe 11:10AM - 12:00PM",
      "room": "Science C205",
      "instr": "Jerry Waxman",
      "status": "Open",
      "htmlKey": "MTG_CLASSNAME$0"
    },
    {
      "title": "CSCI   12 - Introduction to Computers and Computation",
      "nbr": "65367",
      "time": "TuFr 11:10AM - 12:00PM",
      "room": "Science A103",
      "instr": "Changlin Li",
      "status": "Open",
      "htmlKey": "MTG_CLASSNAME$1"
    },
    {
      "title": "CSCI   12 - Introduction to Computers and Computation",
      "nbr": "65372",
      "time": "MoWe 3:50PM - 4:40PM",
      "room": "Science C205",
      "instr": "Jerry Waxman",
      "status": "Open",
      "htmlKey": "MTG_CLASSNAME$2"
    },
    {
      "title": "CSCI   12 - Introduction to Computers and Computation",
      "nbr": "65374",
      "time": "TuTh 2:45PM - 3:35PM",
      "room": "Science A103",
      "instr": "Yuqian Zhang",
      "status": "Open",
      "htmlKey": "MTG_CLASSNAME$3"
    },
    {
      "title": "CSCI   12 - Introduction to Computers and Computation",
      "nbr": "65376",
      "time": "TuTh 1:40PM - 2:30PM",
      "room": "Science A103",
      "instr": "Kiyoung Song",
      "status": "Open",
      "htmlKey": "MTG_CLASSNAME$4"
    },
    {
      "title": "CSCI   12 - Introduction to Computers and Computation",
      "nbr": "65379",
      "time": "TuTh 3:50PM - 4:40PM",
      "room": "Science A103",
      "instr": "Staff",
      "status": "Open",
      "htmlKey": "MTG_CLASSNAME$5"
    },
    {
      "title": "CSCI   12 - Introduction to Computers and Computation",
      "nbr": "65357",
      "time": "MoWe 7:30PM - 8:20PM",
      "room": "Science C205",
      "instr": "Aryeh Greenberg",
      "status": "Open",
      "htmlKey": "MTG_CLASSNAME$6"
    },
    {
      "title": "CSCI   12 - Introduction to Computers and Computation",
      "nbr": "65358",
      "time": "MoWe 8:30PM - 9:20PM",
      "room": "Science A135B",
      "instr": "Aryeh Greenberg",
      "status": "Open",
      "htmlKey": "MTG_CLASSNAME$7"
    },
    {
      "title": "CSCI   12 - Introduction to Computers and Computation",
      "nbr": "65361",
      "time": "Su 1:00PM - 2:50PM",
      "room": "Science B131",
      "instr": "Dorothy Nixon",
      "status": "Open",
      "htmlKey": "MTG_CLASSNAME$8"
    },
    {
      "title": "CSCI   12 - Introduction to Computers and Computation",
      "nbr": "65362",
      "time": "Su 3:00PM - 4:50PM",
      "room": "Science B131",
      "instr": "Dorothy Nixon",
      "status": "Open",
      "htmlKey": "MTG_CLASSNAME$9"
    },
    {
      "title": "CSCI   81 - Introduction to Web Programming",
      "nbr": "65344",
      "time": "MoWe 6:30PM - 7:45PM",
      "room": "Science A103",
      "instr": "Raymond Law",
      "status": "Open",
      "htmlKey": "MTG_CLASSNAME$10"
    },
    {
      "title": "CSCI   90 - Topics in Computing",
      "nbr": "65338",
      "time": "MoWe 9:15AM - 10:30AM",
      "room": "Science A103",
      "instr": "Theodore Brown",
      "status": "Open",
      "htmlKey": "MTG_CLASSNAME$11"
    },
    {
      "title": "CSCI   90 - Topics in Computing",
      "nbr": "69532",
      "time": "TuFr 8:00AM - 8:50AM\rFr 9:00AM - 9:50AM",
      "room": "Science B145\rScience B131",
      "instr": "Anne Smith-Thompson\rAnne Smith-Thompson",
      "status": "Open",
      "htmlKey": "MTG_CLASSNAME$12"
    },
    {
      "title": "CSCI   90 - Topics in Computing",
      "nbr": "65347",
      "time": "MoWe 8:00PM - 9:15PM",
      "room": "Science A103",
      "instr": "Raymond Law",
      "status": "Open",
      "htmlKey": "MTG_CLASSNAME$13"
    },
    {
      "title": "CSCI  111 - Introduction to Algorithmic Problem - Solving",
      "nbr": "65389",
      "time": "MoWe 9:00AM - 9:50AM",
      "room": "Science C205",
      "instr": "Alexander Ryba",
      "status": "Open",
      "htmlKey": "MTG_CLASSNAME$14"
    },
    {
      "title": "CSCI  111 - Introduction to Algorithmic Problem - Solving",
      "nbr": "65398",
      "time": "MoWe 2:45PM - 3:35PM",
      "room": "Science C205",
      "instr": "Alexander Ryba",
      "status": "Open",
      "htmlKey": "MTG_CLASSNAME$15"
    },
    {
      "title": "CSCI  111 - Introduction to Algorithmic Problem - Solving",
      "nbr": "65381",
      "time": "MoWe 5:00PM - 5:50PM",
      "room": "Science C205",
      "instr": "Sara Geizhals",
      "status": "Open",
      "htmlKey": "MTG_CLASSNAME$16"
    },
    {
      "title": "CSCI  111 - Introduction to Algorithmic Problem - Solving",
      "nbr": "65386",
      "time": "TuTh 6:30PM - 7:20PM",
      "room": "Science B131",
      "instr": "Robert Mashburn",
      "status": "Open",
      "htmlKey": "MTG_CLASSNAME$17"
    },
    {
      "title": "CSCI  211 - Object-Oriented Programming in C++",
      "nbr": "76838",
      "time": "TuTh 9:00AM - 9:50AM",
      "room": "Science B137",
      "instr": "Eric Dagobert",
      "status": "Open",
      "htmlKey": "MTG_CLASSNAME$18"
    },
    {
      "title": "CSCI  211 - Object-Oriented Programming in C++",
      "nbr": "65418",
      "time": "MoWe 1:40PM - 2:30PM",
      "room": "Science C205",
      "instr": "Jerry Waxman",
      "status": "Open",
      "htmlKey": "MTG_CLASSNAME$19"
    },
    {
      "title": "CSCI  211 - Object-Oriented Programming in C++",
      "nbr": "65421",
      "time": "MoWe 8:00AM - 8:50AM",
      "room": "Science A223",
      "instr": "Guozhen An",
      "status": "Open",
      "htmlKey": "MTG_CLASSNAME$20"
    },
    {
      "title": "CSCI  211 - Object-Oriented Programming in C++",
      "nbr": "65427",
      "time": "MoWe 10:05AM - 10:55AM",
      "room": "Science A135B",
      "instr": "Guozhen An",
      "status": "Open",
      "htmlKey": "MTG_CLASSNAME$21"
    },
    {
      "title": "CSCI  211 - Object-Oriented Programming in C++",
      "nbr": "65413",
      "time": "TuTh 8:30PM - 9:20PM",
      "room": "Science C205",
      "instr": "Yosef Alayev",
      "status": "Open",
      "htmlKey": "MTG_CLASSNAME$22"
    },
    {
      "title": "CSCI  211 - Object-Oriented Programming in C++",
      "nbr": "65414",
      "time": "MoWe 7:30PM - 8:20PM",
      "room": "Science A223",
      "instr": "Andy Abreu",
      "status": "Open",
      "htmlKey": "MTG_CLASSNAME$23"
    },
    {
      "title": "CSCI  211 - Object-Oriented Programming in C++",
      "nbr": "65417",
      "time": "MoWe 7:30PM - 8:20PM",
      "room": "Science A135B",
      "instr": "Kangmei Yang",
      "status": "Open",
      "htmlKey": "MTG_CLASSNAME$24"
    },
    {
      "title": "CSCI  212 - Object-Oriented Programming in Java",
      "nbr": "65431",
      "time": "MoWe 10:05AM - 10:55AM",
      "room": "Science C205",
      "instr": "Kenneth Lord",
      "status": "Open",
      "htmlKey": "MTG_CLASSNAME$25"
    },
    {
      "title": "CSCI  212 - Object-Oriented Programming in Java",
      "nbr": "76577",
      "time": "TuTh 1:40PM - 2:30PM",
      "room": "Science C207",
      "instr": "Kok Teng Lee",
      "status": "Open",
      "htmlKey": "MTG_CLASSNAME$26"
    },
    {
      "title": "CSCI  212 - Object-Oriented Programming in Java",
      "nbr": "76579",
      "time": "TuTh 3:50PM - 4:40PM",
      "room": "Science A135H",
      "instr": "Kiyoung Song",
      "status": "Open",
      "htmlKey": "MTG_CLASSNAME$27"
    },
    {
      "title": "CSCI  212 - Object-Oriented Programming in Java",
      "nbr": "65428",
      "time": "MoWe 6:30PM - 7:20PM",
      "room": "Science C205",
      "instr": "Daniel Gutlove",
      "status": "Open",
      "htmlKey": "MTG_CLASSNAME$28"
    },
    {
      "title": "CSCI  212 - Object-Oriented Programming in Java",
      "nbr": "65429",
      "time": "TuTh 6:30PM - 7:20PM",
      "room": "Science A223",
      "instr": "Kok Teng Lee",
      "status": "Open",
      "htmlKey": "MTG_CLASSNAME$29"
    },
    {
      "title": "CSCI  240 - Computer Organization and Assembly Language",
      "nbr": "66728",
      "time": "TuFr 9:15AM - 10:30AM",
      "room": "Science B141",
      "instr": "Simina Fluture",
      "status": "Open",
      "htmlKey": "MTG_CLASSNAME$30"
    },
    {
      "title": "CSCI  313 - Data Structures",
      "nbr": "66662",
      "time": "MoWe 10:45AM - 12:00PM",
      "room": "Science B141",
      "instr": "Joseph Svitak",
      "status": "Open",
      "htmlKey": "MTG_CLASSNAME$31"
    },
    {
      "title": "CSCI  313 - Data Structures",
      "nbr": "66667",
      "time": "TuTh 8:00PM - 9:15PM",
      "room": "Science B141",
      "instr": "Joseph Svitak",
      "status": "Open",
      "htmlKey": "MTG_CLASSNAME$32"
    },
    {
      "title": "CSCI  320 - Theory of Computation",
      "nbr": "66690",
      "time": "TuTh 3:10PM - 4:25PM",
      "room": "Science B141",
      "instr": "Kent Boklan",
      "status": "Open",
      "htmlKey": "MTG_CLASSNAME$33"
    },
    {
      "title": "CSCI  320 - Theory of Computation",
      "nbr": "66694",
      "time": "TuTh 6:30PM - 7:45PM",
      "room": "Science B141",
      "instr": "Kent Boklan",
      "status": "Open",
      "htmlKey": "MTG_CLASSNAME$34"
    },
    {
      "title": "CSCI  323 - Design and Analysis of Algorithms",
      "nbr": "66562",
      "time": "We 6:30PM - 9:20PM",
      "room": "Science D133",
      "instr": "Lawrence Teitelman",
      "status": "Open",
      "htmlKey": "MTG_CLASSNAME$35"
    },
    {
      "title": "CSCI  323 - Design and Analysis of Algorithms",
      "nbr": "66050",
      "time": "TuTh 8:00PM - 9:15PM",
      "room": "Science B145",
      "instr": "Tsaiyun Phillips",
      "status": "Open",
      "htmlKey": "MTG_CLASSNAME$36"
    },
    {
      "title": "CSCI  331 - Database Systems",
      "nbr": "66047",
      "time": "MoWe 10:45AM - 12:00PM",
      "room": "Remsen 017",
      "instr": "Bojana Obrenic",
      "status": "Open",
      "htmlKey": "MTG_CLASSNAME$37"
    },
    {
      "title": "CSCI  340 - Operating Systems Principles",
      "nbr": "66634",
      "time": "TuFr 10:45AM - 12:00PM",
      "room": "Powdermker 132",
      "instr": "Simina Fluture",
      "status": "Open",
      "htmlKey": "MTG_CLASSNAME$38"
    },
    {
      "title": "CSCI  344 - Distributed Systems",
      "nbr": "66053",
      "time": "MoWe 1:40PM - 2:55PM",
      "room": "Science B145",
      "instr": "Simina Fluture",
      "status": "Open",
      "htmlKey": "MTG_CLASSNAME$39"
    },
    {
      "title": "CSCI  363 - Artificial Intelligence",
      "nbr": "66045",
      "time": "Fr 9:10AM - 12:00PM",
      "room": "Science D135",
      "instr": "Changhe Yuan",
      "status": "Open",
      "htmlKey": "MTG_CLASSNAME$40"
    },
    {
      "title": "CSCI  381 - Special Topics in Computer Science",
      "nbr": "66515",
      "time": "TuTh 1:40PM - 2:55PM",
      "room": "Science D135",
      "instr": "Chao Chen",
      "status": "Open",
      "htmlKey": "MTG_CLASSNAME$41"
    },
    {
      "title": "CSCI  700 - Algorithms I",
      "nbr": "66570",
      "time": "We 6:30PM - 9:20PM",
      "room": "Science D133",
      "instr": "Lawrence Teitelman",
      "status": "Open",
      "htmlKey": "MTG_CLASSNAME$42"
    },
    {
      "title": "CSCI  700 - Algorithms I",
      "nbr": "66051",
      "time": "TuTh 5:00PM - 6:15PM",
      "room": "Science B145",
      "instr": "Tsaiyun Phillips",
      "status": "Open",
      "htmlKey": "MTG_CLASSNAME$43"
    },
    {
      "title": "CSCI  700 - Algorithms I",
      "nbr": "66052",
      "time": "TuTh 8:00PM - 9:15PM",
      "room": "Science B145",
      "instr": "Tsaiyun Phillips",
      "status": "Open",
      "htmlKey": "MTG_CLASSNAME$44"
    },
    {
      "title": "CSCI  715 - Distributed Computing",
      "nbr": "66054",
      "time": "MoWe 1:40PM - 2:55PM",
      "room": "Science B145",
      "instr": "Simina Fluture",
      "status": "Open",
      "htmlKey": "MTG_CLASSNAME$45"
    },
    {
      "title": "CSCI  744 - Computer Architecture and Networks",
      "nbr": "68673",
      "time": "MoTuWeTh 7:00PM - 10:13PM",
      "room": "Science C205",
      "instr": "Vivek Upadhyay",
      "status": "Open",
      "htmlKey": "MTG_CLASSNAME$46"
    },
    {
      "title": "CSCI  780 - Special Topics in Computer Science",
      "nbr": "66065",
      "time": "TuTh 10:45AM - 12:00PM",
      "room": "Science D135",
      "instr": "Bon Sy",
      "status": "Open",
      "htmlKey": "MTG_CLASSNAME$47"
    },
    {
      "title": "CSCI  780 - Special Topics in Computer Science",
      "nbr": "67781",
      "time": "MoTuWeTh 9:30AM - 12:43PM",
      "room": "Science D135",
      "instr": "Changhe Yuan",
      "status": "Open",
      "htmlKey": "MTG_CLASSNAME$48"
    },
    {
      "title": "CSCI  780 - Special Topics in Computer Science",
      "nbr": "66518",
      "time": "TuTh 1:40PM - 2:55PM",
      "room": "Science D135",
      "instr": "Chao Chen",
      "status": "Open",
      "htmlKey": "MTG_CLASSNAME$49"
    },
    {
      "title": "CSCI  780 - Special Topics in Computer Science",
      "nbr": "66541",
      "time": "TuTh 5:00PM - 6:15PM",
      "room": "Science B141",
      "instr": "Keitaro Yukawa",
      "status": "Open",
      "htmlKey": "MTG_CLASSNAME$50"
    }
  ]
}
